{
  "fleet": "input/de/fleet/Kraftwerke_eff_binned.csv",
  "eta_col": "Imputed_Effizienz_binned",
  "fuel_prices": "input/de/fuels/prices_2024.csv",
  "flows": "flows/flows_scheduled_DE_LU_2024_net.csv",
  "flow_mode": "scheduled",
  "start": "2024-01-01",
  "end": "2025-01-01",
  "neighbor_gen_dir": "input/neighbors/gen_2024",
  "neighbor_load_dir": "input/neighbors/out_load/2024",
  "neighbor_prices": "input/neighbors/prices/neighbor_prices_2024.csv",
  "epsilon": 0.01,
  "price_anchor": "threshold",
  "price_tol": 30.0,
  "reservoir_max_clip": 300.0,
  "reservoir_max_srmc": 300.0,
  "jao_fb_enable": true,
  "jao_fb_tolerance": 100.0,
  "ee_price_threshold": 10.0,
  "import_zero_price_threshold": 10.0,
  "ee_gate_tol": 0.01,
  "domestic_ee_after_mustrun": true,
  "ee_surplus_order": "mu_before_ee",
  "year": 2024,
  "outdir": "out/full_year_requested_ee"
}